oligo_designer_toolsuite/__init__.py
oligo_designer_toolsuite/_constants.py
oligo_designer_toolsuite/_version.py
oligo_designer_toolsuite/database/__init__.py
oligo_designer_toolsuite/database/_oligo_database.py
oligo_designer_toolsuite/database/_oligo_database_attributes.py
oligo_designer_toolsuite/database/_reference_database.py
oligo_designer_toolsuite/oligo_efficiency_filter/__init__.py
oligo_designer_toolsuite/oligo_efficiency_filter/_oligo_scoring.py
oligo_designer_toolsuite/oligo_efficiency_filter/_set_scoring.py
oligo_designer_toolsuite/oligo_property_filter/__init__.py
oligo_designer_toolsuite/oligo_property_filter/_filter_base.py
oligo_designer_toolsuite/oligo_property_filter/_filter_experiment_specific.py
oligo_designer_toolsuite/oligo_property_filter/_filter_experiment_unspecific.py
oligo_designer_toolsuite/oligo_property_filter/_property_filter.py
oligo_designer_toolsuite/oligo_selection/__init__.py
oligo_designer_toolsuite/oligo_selection/_generate_oligosets.py
oligo_designer_toolsuite/oligo_selection/_selection_methods.py
oligo_designer_toolsuite/oligo_specificity_filter/__init__.py
oligo_designer_toolsuite/oligo_specificity_filter/_filter_ai.py
oligo_designer_toolsuite/oligo_specificity_filter/_filter_base.py
oligo_designer_toolsuite/oligo_specificity_filter/_filter_blastn.py
oligo_designer_toolsuite/oligo_specificity_filter/_filter_bowtie.py
oligo_designer_toolsuite/oligo_specificity_filter/_filter_cross_hybridization.py
oligo_designer_toolsuite/oligo_specificity_filter/_filter_exact_matches.py
oligo_designer_toolsuite/oligo_specificity_filter/_policies.py
oligo_designer_toolsuite/oligo_specificity_filter/_specificity_filter.py
oligo_designer_toolsuite/pipelines/__init__.py
oligo_designer_toolsuite/pipelines/_genomic_region_generator.py
oligo_designer_toolsuite/pipelines/_merfish_probe_designer.py
oligo_designer_toolsuite/pipelines/_oligo_seq_probe_designer.py
oligo_designer_toolsuite/pipelines/_scrinshot_probe_designer.py
oligo_designer_toolsuite-1.0.1.dist-info/LICENSE
oligo_designer_toolsuite-1.0.1.dist-info/METADATA
oligo_designer_toolsuite-1.0.1.dist-info/WHEEL
oligo_designer_toolsuite-1.0.1.dist-info/entry_points.txt
oligo_designer_toolsuite-1.0.1.dist-info/top_level.txt
oligo_designer_toolsuite-1.0.1.dist-info/RECORD
