Metadata-Version: 2.2
Name: oligo-designer-toolsuite
Version: 1.0.1
Summary: Develop custom oligo design pipelines.
Author: Lisa Barros de Andrade e Sousa, Isra Mekki, Francesco Campi, Louis Kümmerle, Chelsea Bright
Maintainer-email: Lisa Barros de Andrade e Sousa <lisa.barros.andrade.sousa@gmail.com>, Isra Mekki <isra.mekki@helmholtz-muenchen.de>
Project-URL: documentation, https://oligo-designer-toolsuite.readthedocs.io/
Project-URL: repository, https://github.com/HelmholtzAI-Consultants-Munich/oligo-designer-toolsuite
Keywords: bioinformatics,probes,oligo nucleotides,probe design,oligo design
Classifier: Programming Language :: Python :: 3
Classifier: License :: OSI Approved :: MIT License
Classifier: Operating System :: OS Independent
Requires-Python: >=3.9
License-File: LICENSE
Requires-Dist: datetime
Requires-Dist: argparse
Requires-Dist: numpy
Requires-Dist: pandas
Requires-Dist: scipy
Requires-Dist: iteration_utilities
Requires-Dist: Bio
Requires-Dist: pyyaml
Requires-Dist: networkx
Requires-Dist: joblib
Requires-Dist: seqfold
Requires-Dist: effidict
Requires-Dist: joblib_progress
Requires-Dist: oligo-designer-toolsuite-ai-filters
Requires-Dist: ipywidgets
Provides-Extra: dev
Requires-Dist: pytest; extra == "dev"
